Source/rtl/deskew.sv
//////////////////////////////////////////////////////////////////////////////////////////////
// File Name        :  deskew.sv
// Description      :  deskew.sv is the design module that aligns (deskews) two incoming 4-bit
//                     data streams when the value 4'hA is detected on both inputs within a 
//                     maximum skew of two clock cycles. It uses a finite state machine (FSM),
//                     small buffers, and flags to track which stream detects A first and to
//                     delay the earlier stream as needed. Once both streams are aligned, the
//                     module outputs the concatenated 8-bit stream (o_stream) with the 
//                     first-detected stream placed in the LSBs and asserts o_aligned to 
//                     indicate successful alignment.
// Inputs           :  Clock, Reset (Active High), Stream 1 and Stream 2
// Outputs          :  Aligned Flag and Aligned Stream  
//////////////////////////////////////////////////////////////////////////////////////////////

module deskew (
    input       i_clk,      // Inputs
    input       i_reset,    // Synchrnous Reset
    input [3:0] i_stream1,
    input [3:0] i_stream2,

    output reg [7:0] o_stream,  // Outputs
    output reg       o_aligned
);
  localparam IDLE = 0,  // States of the FSM 
  BOTH = 1, AFIRST = 2, BFIRST = 3, A1FIRST = 4, B1FIRST = 5;

  // Internal Registers
  reg [2:0] state, next_state;
  reg [3:0] buffer[0:1];
  reg [1:0] flag;

  // State Transiton Logic
  always @(posedge i_clk) begin
    if (i_reset) state <= IDLE;
    else state <= next_state;
  end

  // Next State Calculation
  always @(*) begin
    case (state)
      IDLE:
      next_state = (i_stream1 == 4'ha && i_stream2 == 4'ha) ? BOTH : (i_stream1 == 4'ha) ? AFIRST : (i_stream2 == 4'ha) ? BFIRST : IDLE;
      BOTH: next_state = BOTH;
      AFIRST: next_state = (i_stream2 == 4'ha || flag[0] == 1'b1) ? AFIRST : A1FIRST;
      BFIRST: next_state = (i_stream1 == 4'ha || flag[0] == 1'b1) ? BFIRST : B1FIRST;
      A1FIRST: next_state = (i_stream2 == 4'ha || flag[1] == 1'b1) ? A1FIRST : IDLE;
      B1FIRST: next_state = (i_stream1 == 4'ha || flag[1] == 1'b1) ? B1FIRST : IDLE;
      default: next_state = IDLE;
    endcase
  end

  // Output Logic	
  always @(posedge i_clk) begin
    case (state)
      IDLE: begin
        o_aligned <= 1'b0;
        o_stream  <= {8{1'b0}};
        flag      <= 2'd0;
        buffer[1] <= 4'd0;
        buffer[0] <= 4'd0;
        if (i_stream1 == 4'ha && i_stream2 == 4'ha) begin
          o_stream  <= {i_stream1, i_stream2};
          o_aligned <= 1'b1;
        end
      end
      BOTH: begin
        o_aligned <= 1'b1;
        o_stream  <= {i_stream2, i_stream1};
      end
      AFIRST: begin
        flag[0] <= (flag[0] == 1'b1) ? flag[0] : (i_stream2 == 4'ha) ? 1'b1 : 1'b0;
        if (i_stream2 == 4'ha && flag[0] == 1'b0) begin
          o_aligned <= 1'b1;
          o_stream  <= {i_stream2, 4'ha};
          buffer[1] <= buffer[0];
          buffer[0] <= i_stream1;
        end else if (flag[0]) begin
          o_aligned <= 1'b1;
          o_stream  <= {i_stream2, buffer[0]};
          buffer[1] <= buffer[0];
          buffer[0] <= i_stream1;
        end else begin
          buffer[0] <= i_stream1;
        end
      end
      BFIRST: begin
        flag[0] <= (flag[0] == 1'b1) ? flag[0] : (i_stream1 == 4'ha) ? 1'b1 : 1'b0;
        if (i_stream1 == 4'ha && flag[0] == 1'b0) begin
          o_aligned <= 1'b1;
          o_stream  <= {i_stream1, 4'ha};
          buffer[1] <= buffer[0];
          buffer[0] <= i_stream2;
        end else if (flag[0]) begin
          o_aligned <= 1'b1;
          o_stream  <= {i_stream1, buffer[0]};
          buffer[1] <= buffer[0];
          buffer[0] <= i_stream2;
        end else begin
          buffer[0] <= i_stream2;
        end
      end
      A1FIRST: begin
        flag[1] <= (flag[1] == 1'b1) ? flag[1] : (i_stream2 == 4'ha) ? 1'b1 : 1'b0;
        if (i_stream2 == 4'ha && flag[1] == 1'b0) begin
          o_aligned <= 1'b1;
          o_stream  <= {i_stream2, 4'ha};
          buffer[1] <= buffer[0];
          buffer[0] <= i_stream1;
        end else if (flag[1]) begin
          o_aligned <= 1'b1;
          o_stream  <= {i_stream2, buffer[1]};
          buffer[1] <= buffer[0];
          buffer[0] <= i_stream1;
        end else begin
          buffer[1] <= buffer[0];
          buffer[0] <= i_stream1;
        end
      end
      B1FIRST: begin
        flag[1] <= (flag[1] == 1'b1) ? flag[1] : (i_stream1 == 4'ha) ? 1'b1 : 1'b0;
        if (i_stream1 == 4'ha && flag[1] == 1'b0) begin
          o_aligned <= 1'b1;
          o_stream  <= {i_stream1, 4'ha};
          buffer[1] <= buffer[0];
          buffer[0] <= i_stream2;
        end else if (flag[1]) begin
          o_aligned <= 1'b1;
          o_stream  <= {i_stream1, buffer[1]};
          buffer[1] <= buffer[0];
          buffer[0] <= i_stream2;
        end else begin
          buffer[1] <= buffer[0];
          buffer[0] <= i_stream2;
        end
      end
      default: begin
        o_aligned <= 1'b0;
        o_stream  <= {8{1'b0}};
        flag      <= 2'd0;
        buffer[1] <= 4'd0;
        buffer[0] <= 4'd0;
      end
    endcase
  end
endmodule

Source/rtl/tb_deskew.sv
//////////////////////////////////////////////////////////////////////////////////////////////
// File Name        :  tb_deskew.sv
// Description      :  tb_deskew is the testbench module used to verify the functionality of
// 		       the deskew design. It generates the clock and reset, applies various 
// 		       input patterns to i_stream1 and i_stream2 (including skewed arrivals of
// 		       4'hA), and observes the outputs o_stream and o_aligned. The testbench 
// 		       checks whether the DUT correctly aligns the two input streams within 
// 		       the allowed skew, produces the expected concatenated output (especially
// 		       the first 0xAA), and asserts the alignment flag at the proper time.
// Inputs           :  NIL
// Outputs          :  NIL
//////////////////////////////////////////////////////////////////////////////////////////////

module tb_deskew;
  // Input and Output Signals
  reg		i_clk;
  reg		i_reset;
  reg	 [3:0]	i_stream1;
  reg	 [3:0]	i_stream2;

  wire   [7:0]  o_stream;
  wire 	        o_aligned;
  	
  // Clock Generation
  always #5 i_clk = ~i_clk;

  // DUT Instantiation
  deskew dut (
	.i_clk     (i_clk),
	.i_reset   (i_reset),
	.i_stream1 (i_stream1),
        .i_stream2 (i_stream2),
	.o_stream  (o_stream),
	.o_aligned (o_aligned)
  );
  
  // Initial Block
  initial begin
    i_clk = 1'b0; i_reset = 1'b1;
    i_stream1 = 4'hd; i_stream2 = 4'hd;
    @(posedge i_clk) i_reset = 1'b0;
    @(posedge i_clk) i_stream1 = 4'hd; i_stream2 = 4'hd; 
    @(posedge i_clk) i_stream1 = 4'ha; i_stream2 = 4'h0;
    @(posedge i_clk) i_stream1 = 4'h0; i_stream2 = 4'h6;    
    @(posedge i_clk) i_stream1 = 4'hb; i_stream2 = 4'ha; 
    @(posedge i_clk) i_stream1 = 4'hd; i_stream2 = 4'hc; 
    @(posedge i_clk) i_stream1 = 4'hf; i_stream2 = 4'h9; 
    @(posedge i_clk) i_stream1 = 4'h6; i_stream2 = 4'hd; 
    @(posedge i_clk) i_stream1 = 4'h9; i_stream2 = 4'hf; 
    @(posedge i_clk) i_stream1 = 4'hc; i_stream2 = 4'h3; 
    @(posedge i_clk) i_stream1 = 4'h7; i_stream2 = 4'h6; 
    @(posedge i_clk) i_stream1 = 4'h6; i_stream2 = 4'hb;

    @(posedge i_clk) i_reset = 1'b1;
    @(posedge i_clk) i_reset = 1'b0;

    @(posedge i_clk) i_stream1 = 4'h3; i_stream2 = 4'h7; 
    @(posedge i_clk) i_stream1 = 4'h8; i_stream2 = 4'h5;
    @(posedge i_clk) i_stream1 = 4'h9; i_stream2 = 4'ha;
    @(posedge i_clk) i_stream1 = 4'ha; i_stream2 = 4'h2;
    @(posedge i_clk) i_stream1 = 4'h5; i_stream2 = 4'h1;
    @(posedge i_clk) i_stream1 = 4'h4; i_stream2 = 4'h3;
    @(posedge i_clk) i_stream1 = 4'h7; i_stream2 = 4'h8;
    @(posedge i_clk) i_stream1 = 4'h2; i_stream2 = 4'h9;
    @(posedge i_clk) i_stream1 = 4'h1; i_stream2 = 4'h6;
    @(posedge i_clk) i_stream1 = 4'hc; i_stream2 = 4'hb;
    @(posedge i_clk) i_stream1 = 4'he; i_stream2 = 4'h0;

    @(posedge i_clk) i_reset = 1'b1;
    @(posedge i_clk) i_reset = 1'b0;

    @(posedge i_clk) i_stream1 = 4'hd; i_stream2 = 4'h0;
    @(posedge i_clk) i_stream1 = 4'ha; i_stream2 = 4'ha;
    @(posedge i_clk) i_stream1 = 4'hc; i_stream2 = 4'hd;
    @(posedge i_clk) i_stream1 = 4'h4; i_stream2 = 4'he;
    @(posedge i_clk) i_stream1 = 4'h5; i_stream2 = 4'h6;
    @(posedge i_clk) i_stream1 = 4'h8; i_stream2 = 4'h3;
    @(posedge i_clk) i_stream1 = 4'h1; i_stream2 = 4'h8;
    @(posedge i_clk) i_stream1 = 4'h0; i_stream2 = 4'h1;
    @(posedge i_clk) i_stream1 = 4'hb; i_stream2 = 4'h0;
    @(posedge i_clk) i_stream1 = 4'hf; i_stream2 = 4'h7;
    @(posedge i_clk) i_stream1 = 4'h9; i_stream2 = 4'hc;
    @(posedge i_clk) i_stream1 = 4'h0; i_stream2 = 4'he;

    @(posedge i_clk) i_reset = 1'b1;
    @(posedge i_clk) i_reset = 1'b0;

    @(posedge i_clk) i_stream1 = 4'hd; i_stream2 = 4'h0;
    @(posedge i_clk) i_stream1 = 4'h5; i_stream2 = 4'ha;
    @(posedge i_clk) i_stream1 = 4'hc; i_stream2 = 4'hd;
    @(posedge i_clk) i_stream1 = 4'h4; i_stream2 = 4'he;
    @(posedge i_clk) i_stream1 = 4'h5; i_stream2 = 4'h6;
    @(posedge i_clk) i_stream1 = 4'ha; i_stream2 = 4'h3;
    @(posedge i_clk) i_stream1 = 4'h1; i_stream2 = 4'ha;
    @(posedge i_clk) i_stream1 = 4'h0; i_stream2 = 4'h1;
    @(posedge i_clk) i_stream1 = 4'hb; i_stream2 = 4'h0;
    @(posedge i_clk) i_stream1 = 4'hf; i_stream2 = 4'h7;
    @(posedge i_clk) i_stream1 = 4'h9; i_stream2 = 4'hc;
    @(posedge i_clk) i_stream1 = 4'h0; i_stream2 = 4'he;
    @(posedge i_clk) i_stream1 = 4'hd; i_stream2 = 4'h0;
    @(posedge i_clk) i_stream1 = 4'ha; i_stream2 = 4'ha;
    @(posedge i_clk) i_stream1 = 4'hc; i_stream2 = 4'hd;
    @(posedge i_clk) i_stream1 = 4'h4; i_stream2 = 4'he;
    @(posedge i_clk) i_stream1 = 4'h5; i_stream2 = 4'h6;
    @(posedge i_clk) i_stream1 = 4'h8; i_stream2 = 4'h3;
    @(posedge i_clk) i_stream1 = 4'h1; i_stream2 = 4'h8;
    @(posedge i_clk) i_stream1 = 4'h0; i_stream2 = 4'h1;
    @(posedge i_clk) i_stream1 = 4'hb; i_stream2 = 4'h0;
    @(posedge i_clk) i_stream1 = 4'hf; i_stream2 = 4'h7;
    @(posedge i_clk) i_stream1 = 4'h9; i_stream2 = 4'hc;
    @(posedge i_clk) i_stream1 = 4'h0; i_stream2 = 4'he;

    @(posedge i_clk) i_reset = 1'b1;
    @(posedge i_clk) i_reset = 1'b0;

    @(posedge i_clk) i_stream1 = 4'hd; i_stream2 = 4'h0;
    @(posedge i_clk) i_stream1 = 4'ha; i_stream2 = 4'h0;
    @(posedge i_clk) i_stream1 = 4'hc; i_stream2 = 4'hd;
    @(posedge i_clk) i_stream1 = 4'h4; i_stream2 = 4'he;
    @(posedge i_clk) i_stream1 = 4'h5; i_stream2 = 4'h6;
    @(posedge i_clk) i_stream1 = 4'h3; i_stream2 = 4'ha;
    @(posedge i_clk) i_stream1 = 4'h1; i_stream2 = 4'ha;
    @(posedge i_clk) i_stream1 = 4'ha; i_stream2 = 4'h1;
    @(posedge i_clk) i_stream1 = 4'hb; i_stream2 = 4'h0;
    @(posedge i_clk) i_stream1 = 4'hf; i_stream2 = 4'h7;
    @(posedge i_clk) i_stream1 = 4'h9; i_stream2 = 4'hc;
    @(posedge i_clk) i_stream1 = 4'h0; i_stream2 = 4'he;
    @(posedge i_clk) i_stream1 = 4'hd; i_stream2 = 4'h0;
    @(posedge i_clk) i_stream1 = 4'ha; i_stream2 = 4'ha;
    @(posedge i_clk) i_stream1 = 4'hc; i_stream2 = 4'hd;
    @(posedge i_clk) i_stream1 = 4'h4; i_stream2 = 4'he;
    @(posedge i_clk) i_stream1 = 4'h5; i_stream2 = 4'h6;
    @(posedge i_clk) i_stream1 = 4'h8; i_stream2 = 4'h3;
    @(posedge i_clk) i_stream1 = 4'h1; i_stream2 = 4'h8;
    @(posedge i_clk) i_stream1 = 4'h0; i_stream2 = 4'h1;
    @(posedge i_clk) i_stream1 = 4'hb; i_stream2 = 4'h0;
    @(posedge i_clk) i_stream1 = 4'hf; i_stream2 = 4'h7;
    @(posedge i_clk) i_stream1 = 4'h9; i_stream2 = 4'hc;
    @(posedge i_clk) i_stream1 = 4'h0; i_stream2 = 4'he;

    @(posedge i_clk) i_reset = 1'b1;
    @(posedge i_clk) i_reset = 1'b0;

    @(posedge i_clk) i_reset = 1'b0;
    @(posedge i_clk) i_stream1 = 4'hd; i_stream2 = 4'hd; 
    @(posedge i_clk) i_stream1 = 4'h0; i_stream2 = 4'ha;
    @(posedge i_clk) i_stream1 = 4'h0; i_stream2 = 4'h6;    
    @(posedge i_clk) i_stream1 = 4'ha; i_stream2 = 4'h0; 
    @(posedge i_clk) i_stream1 = 4'hd; i_stream2 = 4'hc; 
    @(posedge i_clk) i_stream1 = 4'hf; i_stream2 = 4'h9; 
    @(posedge i_clk) i_stream1 = 4'h6; i_stream2 = 4'hd; 
    @(posedge i_clk) i_stream1 = 4'h9; i_stream2 = 4'hf; 
    @(posedge i_clk) i_stream1 = 4'hc; i_stream2 = 4'h3; 
    @(posedge i_clk) i_stream1 = 4'h7; i_stream2 = 4'h6; 
    @(posedge i_clk) i_stream1 = 4'h6; i_stream2 = 4'hb;

    @(posedge i_clk) i_reset = 1'b1;
    @(posedge i_clk) i_reset = 1'b0;

    @(posedge i_clk) i_stream1 = 4'h3; i_stream2 = 4'h7; 
    @(posedge i_clk) i_stream1 = 4'h8; i_stream2 = 4'ha;
    @(posedge i_clk) i_stream1 = 4'ha; i_stream2 = 4'h5;
    @(posedge i_clk) i_stream1 = 4'ha; i_stream2 = 4'h2;
    @(posedge i_clk) i_stream1 = 4'h5; i_stream2 = 4'h1;
    @(posedge i_clk) i_stream1 = 4'h4; i_stream2 = 4'h3;
    @(posedge i_clk) i_stream1 = 4'h7; i_stream2 = 4'h8;
    @(posedge i_clk) i_stream1 = 4'h2; i_stream2 = 4'h9;
    @(posedge i_clk) i_stream1 = 4'h1; i_stream2 = 4'h6;
    @(posedge i_clk) i_stream1 = 4'hc; i_stream2 = 4'hb;
    @(posedge i_clk) i_stream1 = 4'he; i_stream2 = 4'h0;

    @(posedge i_clk) i_reset = 1'b1;
    @(posedge i_clk) i_reset = 1'b0;

    @(posedge i_clk) i_stream1 = 4'h3; i_stream2 = 4'h7; 
    @(posedge i_clk) i_stream1 = 4'ha; i_stream2 = 4'h4;
    @(posedge i_clk) i_stream1 = 4'h4; i_stream2 = 4'h5;
    @(posedge i_clk) i_stream1 = 4'h7; i_stream2 = 4'ha;
    @(posedge i_clk) i_stream1 = 4'h5; i_stream2 = 4'h1;
    @(posedge i_clk) i_stream1 = 4'h4; i_stream2 = 4'h3;
    @(posedge i_clk) i_stream1 = 4'h7; i_stream2 = 4'h8;
    @(posedge i_clk) i_stream1 = 4'h2; i_stream2 = 4'h9;
    @(posedge i_clk) i_stream1 = 4'h1; i_stream2 = 4'h6;
    @(posedge i_clk) i_stream1 = 4'hc; i_stream2 = 4'hb;
    @(posedge i_clk) i_stream1 = 4'he; i_stream2 = 4'h0;

    @(posedge i_clk) i_reset = 1'b1;
    @(posedge i_clk) i_reset = 1'b0;

    @(posedge i_clk) i_stream1 = 4'hd; i_stream2 = 4'h0;
    @(posedge i_clk) i_stream1 = 4'ha; i_stream2 = 4'h0;
    @(posedge i_clk) i_stream1 = 4'hc; i_stream2 = 4'hd;
    @(posedge i_clk) i_stream1 = 4'h4; i_stream2 = 4'he;
    @(posedge i_clk) i_stream1 = 4'h5; i_stream2 = 4'h6;
    @(posedge i_clk) i_stream1 = 4'ha; i_stream2 = 4'h4;
    @(posedge i_clk) i_stream1 = 4'h3; i_stream2 = 4'h1;
    @(posedge i_clk) i_stream1 = 4'h0; i_stream2 = 4'ha;
    @(posedge i_clk) i_stream1 = 4'hb; i_stream2 = 4'h0;
    @(posedge i_clk) i_stream1 = 4'hf; i_stream2 = 4'h7;
    @(posedge i_clk) i_stream1 = 4'h9; i_stream2 = 4'hc;
    @(posedge i_clk) i_stream1 = 4'h0; i_stream2 = 4'he;
    @(posedge i_clk) i_stream1 = 4'hd; i_stream2 = 4'h0;
    @(posedge i_clk) i_stream1 = 4'ha; i_stream2 = 4'ha;
    @(posedge i_clk) i_stream1 = 4'hc; i_stream2 = 4'hd;
    @(posedge i_clk) i_stream1 = 4'h4; i_stream2 = 4'he;
    @(posedge i_clk) i_stream1 = 4'h5; i_stream2 = 4'h6;
    @(posedge i_clk) i_stream1 = 4'h8; i_stream2 = 4'h3;
    @(posedge i_clk) i_stream1 = 4'h1; i_stream2 = 4'h8;
    @(posedge i_clk) i_stream1 = 4'h0; i_stream2 = 4'h1;
    @(posedge i_clk) i_stream1 = 4'hb; i_stream2 = 4'h0;
    @(posedge i_clk) i_stream1 = 4'hf; i_stream2 = 4'h7;
    @(posedge i_clk) i_stream1 = 4'h9; i_stream2 = 4'hc;
    @(posedge i_clk) i_stream1 = 4'h0; i_stream2 = 4'he;



    @(posedge i_clk) i_reset = 1'b1;
    @(posedge i_clk) i_reset = 1'b0;

    repeat(2) @(posedge i_clk);
    $finish;
  end
endmodule

Source/rtl/dump.vcd
$date
	Tue Mar 10 13:57:03 2026
$end
$version
	QuestaSim Version 2021.2_1
$end
$timescale
	1ns
$end

$scope module tb_deskew $end
$var reg 1 ! i_clk $end

$scope module dut $end
$var parameter 32 " IDLE $end
$var parameter 32 # BOTH $end
$var parameter 32 $ AFIRST $end
$var parameter 32 % BFIRST $end
$var parameter 32 & A1FIRST $end
$var parameter 32 ' B1FIRST $end
$var wire 1 ( i_clk $end
$var wire 1 ) i_reset $end
$var wire 1 * i_stream1 [3] $end
$var wire 1 + i_stream1 [2] $end
$var wire 1 , i_stream1 [1] $end
$var wire 1 - i_stream1 [0] $end
$var wire 1 . i_stream2 [3] $end
$var wire 1 / i_stream2 [2] $end
$var wire 1 0 i_stream2 [1] $end
$var wire 1 1 i_stream2 [0] $end
$var reg 8 2 o_stream [7:0] $end
$var reg 1 3 o_aligned $end
$var reg 3 4 state [2:0] $end
$var reg 3 5 next_state [2:0] $end
$var reg 2 6 flag [1:0] $end
$upscope $end
$upscope $end
$enddefinitions $end
#0
$dumpvars
0!
bx 2
x3
bx 4
bx 5
bx 6
b0 "
b1 #
b10 $
b11 %
b100 &
b101 '
x1
x0
x/
x.
x-
x,
x+
x*
x)
0(
$end
#5
1!
1(
03
b0 2
b0 6
b0 5
1)
01
00
0/
0.
0-
0,
0+
0*
#10
0!
0(
#15
1!
1(
b0 4
0)
#20
0!
0(
#25
1!
1(
11
1/
1.
1-
1+
1*
#30
0!
0(
#35
1!
1(
01
0/
0.
0-
1,
0+
b10 5
#40
0!
0(
#45
1!
1(
b10 4
b100 5
10
1/
0,
0*
#50
0!
0(
#55
1!
1(
b100 4
b0 5
0/
1.
1-
1,
1*
b100 5
#60
0!
0(
#65
1!
1(
b10 6
13
b10101010 2
00
1/
0,
1+
#70
0!
0(
#75
1!
1(
b11000000 2
11
0/
1,
#80
0!
0(
#85
1!
1(
b10011011 2
1/
0-
0*
#90
0!
0(
#95
1!
1(
b11011101 2
10
1-
0,
0+
1*
#100
0!
0(
#105
1!
1(
b11111111 2
0/
0.
0-
1+
#110
0!
0(
#115
1!
1(
b110110 2
01
1/
1-
1,
0*
#120
0!
0(
#125
1!
1(
b1101001 2
11
0/
1.
0-
#130
0!
0(
#135
1!
1(
b10111100 2
01
00
1*
#140
0!
0(
#145
1!
1(
b10000111 2
10
1-
#150
0!
0(
#155
1!
1(
b10100110 2
11
00
1/
0.
0,
0+
0*
#160
0!
0(
#165
1!
1(
b1011110 2
10
0/
0-
1+
#170
0!
0(
#175
1!
1(
b111111 2
1/
1,
0+
#180
0!
0(
#185
1!
1(
b1110001 2
1)
01
00
0/
0,
#190
0!
0(
#195
1!
1(
b0 4
b100 2
b0 5
0)
11
1-
#200
0!
0(
#205
1!
1(
03
b0 2
b0 6
#210
0!
0(
#215
1!
1(
01
10
1.
0-
1,
1*
b1 5
#220
0!
0(
#225
1!
1(
b1 4
b10101010 2
13
11
00
1/
0.
1-
0*
#230
0!
0(
#235
1!
1(
b1010011 2
0/
1.
1+
#240
0!
0(
#245
1!
1(
b10010111 2
01
1/
1*
#250
0!
0(
#255
1!
1(
b11001111 2
1)
0/
0.
0-
0,
0+
0*
#260
0!
0(
#265
1!
1(
b0 4
b0 2
b0 5
0)
11
1-
#270
0!
0(
#275
1!
1(
03
#280
0!
0(
#285
1!
1(
1/
0-
1,
1*
b10 5
#290
0!
0(
#295
1!
1(
b10 4
b100 5
01
10
0/
1.
1-
0*
b10 5
#300
0!
0(
#305
1!
1(
b1 6
13
b10101010 2
11
0-
1+
#310
0!
0(
#315
1!
1(
b10110011 2
01
00
1/
1-
0,
0+
1*
#320
0!
0(
#325
1!
1(
b11000110 2
1)
0/
0.
0-
0*
#330
0!
0(
#335
1!
1(
b0 4
b1001 2
b0 5
0)
11
1-
#340
0!
0(
#345
1!
1(
03
b0 2
b0 6
#350
0!
0(
#355
1!
1(
01
10
1.
1+
b11 5
#360
0!
0(
#365
1!
1(
b11 4
b101 5
11
0.
0-
1,
0+
1*
b11 5
#370
0!
0(
#375
1!
1(
b1 6
13
b10101010 2
1/
1-
#380
0!
0(
#385
1!
1(
b10110011 2
01
0/
0-
0,
1+
#390
0!
0(
#395
1!
1(
b11000111 2
1)
00
0+
0*
#400
0!
0(
#405
1!
1(
b0 4
b10 2
b0 5
0)
11
1-
#410
0!
0(
#415
1!
1(
03
b0 2
b0 6
#420
0!
0(
#425
1!
1(
01
10
0-
1,
1*
b10 5
#430
0!
0(
#435
1!
1(
b10 4
b100 5
00
1/
1-
0*
#440
0!
0(
#445
1!
1(
b100 4
b0 5
10
0/
1.
0,
1+
b100 5
#450
0!
0(
#455
1!
1(
b10 6
13
b10101010 2
11
1/
0.
0-
1,
#460
0!
0(
#465
1!
1(
b1110011 2
00
0/
1.
0,
0+
1*
#470
0!
0(
#475
1!
1(
b10010101 2
1)
01
0.
0*
#480
0!
0(
#485
1!
1(
b0 4
b110 2
b0 5
0)
11
1-
#490
0!
0(
#495
1!
1(
03
b0 2
b0 6
#500
0!
0(
#505
1!
1(
01
10
1.
0-
1,
b11 5
#510
0!
0(
#515
1!
1(
b11 4
b101 5
11
0.
0,
1+
#520
0!
0(
#525
1!
1(
b101 4
b0 5
00
1/
1,
0+
1*
b101 5
#530
0!
0(
#535
1!
1(
b10 6
13
b10101010 2
01
10
1-
1+
0*
#540
0!
0(
#545
1!
1(
b1110011 2
00
0/
1.
0,
0+
1*
#550
0!
0(
#555
1!
1(
b10010101 2
1)
0.
0-
0*
#560
0!
0(
#565
1!
1(
b0 4
b110 2
b0 5
0)
11
1-
#570
0!
0(
#575
1!
1(
03
b0 2
b0 6
#580
0!
0(
#585
1!
1(
0-
1,
1*
b10 5
#590
0!
0(
#595
1!
1(
b10 4
b100 5
10
0*
#600
0!
0(
#605
1!
1(
b100 4
b0 5
00
1/
0,
1+
#610
0!
0(
#615
1!
1(
b0 4
0/
1-
0+
#620
0!
0(
#625
1!
1(
#630
0!
0(
#635
1!
1(
#640
0!
0(
#645
1!
1(
1)
01
0-
#650
0!
0(
#655
1!
1(
0)
11
1-
#660
0!
0(
#665
1!
1(
#670
0!
0(
#675
1!
1(
01
10
1.
b11 5
#680
0!
0(
#685
1!
1(
b11 4
b101 5
0.
1,
#690
0!
0(
#695
1!
1(
b101 4
b0 5
00
1/
0,
1+
#700
0!
0(
#705
1!
1(
b0 4
11
0/
0+
#710
0!
0(
#715
1!
1(
#720
0!
0(
#725
1!
1(
#730
0!
0(
#735
1!
1(
1)
01
0-
#740
0!
0(
#745
1!
1(
0)
11
1-
#750
0!
0(
#755
1!
1(
#760
0!
0(
#765
1!
1(
01
10
1.
1,
b11 5
#770
0!
0(
#775
1!
1(
b11 4
b101 5
11
00
1/
0.
0-
1*
b11 5
#780
0!
0(
#785
1!
1(
b1 6
13
b10101010 2
10
1+
0*
#790
0!
0(
#795
1!
1(
b1100101 2
00
0/
1.
0,
0+
1*
#800
0!
0(
#805
1!
1(
b10000111 2
1)
01
0.
0*
#810
0!
0(
#815
1!
1(
b0 4
b1001 2
b0 5
0)
11
1-
#820
0!
0(
#825
1!
1(
03
b0 2
b0 6
#830
0!
0(
#835
1!
1(
01
10
1.
b11 5
#840
0!
0(
#845
1!
1(
b11 4
b101 5
0.
0-
1,
1*
b11 5
#850
0!
0(
#855
1!
1(
b1 6
13
b10101010 2
00
1/
1-
0*
#860
0!
0(
#865
1!
1(
b110010 2
1)
0/
0-
0,
#870
0!
0(
#875
1!
1(
b0 4
b100 2
b0 5
0)
11
1-
#880
0!
0(
#885
1!
1(
03
b0 2
b0 6
#890
0!
0(
#895
1!
1(
01
10
1.
1,
b11 5
#900
0!
0(
#905
1!
1(
b11 4
b101 5
11
00
1/
0.
0-
0,
1+
#910
0!
0(
#915
1!
1(
b101 4
b0 5
01
10
1,
0+
1*
b101 5
#920
0!
0(
#925
1!
1(
b10 6
13
b10101010 2
00
0/
1.
1-
1+
0*
#930
0!
0(
#935
1!
1(
b1110101 2
1/
0,
0+
1*
#940
0!
0(
#945
1!
1(
b10010110 2
1)
0/
0.
0-
0*
#950
0!
0(
#955
1!
1(
b0 4
b1000 2
b0 5
0)
11
1-
#960
0!
0(
#965
1!
1(
03
b0 2
b0 6
#970
0!
0(
#975
1!
1(
01
10
1.
b11 5
#980
0!
0(
#985
1!
1(
b11 4
b101 5
11
0.
0-
1,
#990
0!
0(
#995
1!
1(
b101 4
b0 5
01
00
1/
1*
b101 5
#1000
0!
0(
#1005
1!
1(
b10 6
13
b10101010 2
10
1-
0,
1+
0*
#1010
0!
0(
#1015
1!
1(
b1010011 2
00
0/
1.
1,
#1020
0!
0(
#1025
1!
1(
b1110100 2
11
0.
0,
0+
#1030
0!
0(
#1035
1!
1(
b10110 2
#1040
0!
0(
#1045
1!
1(
b11000 2
10
0-
1,
1*
#1050
0!
0(
#1055
1!
1(
b10100001 2
00
1/
0,
1+
0*
#1060
0!
0(
#1065
1!
1(
b1000001 2
1)
01
0/
0+
#1070
0!
0(
#1075
1!
1(
b0 4
b11 2
b0 5
0)
11
1-
#1080
0!
0(
#1085
1!
1(
03
b0 2
b0 6
#1090
0!
0(
#1095
1!
1(
01
10
1.
0-
1,
1*
b1 5
#1100
0!
0(
#1105
1!
1(
b1 4
b10101010 2
13
1/
1-
0,
1+
#1110
0!
0(
#1115
1!
1(
b11101101 2
0/
0.
1,
#1120
0!
0(
#1125
1!
1(
b101111 2
1)
00
0-
0,
0+
0*
#1130
0!
0(
#1135
1!
1(
b0 4
b0 2
b0 5
0)
11
1-
#1140
0!
0(
#1145
1!
1(
03
#1150
0!
0(
#1155
1!
1(
10
0-
1,
1*
b10 5
#1160
0!
0(
#1165
1!
1(
b10 4
b100 5
01
1.
1-
0,
1+
0*
b10 5
#1170
0!
0(
#1175
1!
1(
b1 6
13
b10101010 2
0-
1,
#1180
0!
0(
#1185
1!
1(
b10100101 2
00
1-
#1190
0!
0(
#1195
1!
1(
b10000110 2
1/
0,
0+
1*
#1200
0!
0(
#1205
1!
1(
b11000111 2
1)
0/
0.
0-
0*
#1210
0!
0(
#1215
1!
1(
b0 4
b1001 2
b0 5
0)
11
1-
#1220
0!
0(
#1225
1!
1(
03
b0 2
b0 6
#1230
0!
0(
#1235
1!
1(
01
10
1.
1,
b11 5
#1240
0!
0(
#1245
1!
1(
b11 4
b101 5
11
00
1/
0.
0-
1*
b11 5
#1250
0!
0(
#1255
1!
1(
b1 6
13
b10101010 2
01
10
#1260
0!
0(
#1265
1!
1(
b10100101 2
00
0/
1.
1-
1+
0*
#1270
0!
0(
#1275
1!
1(
b1110110 2
1/
0,
0+
1*
#1280
0!
0(
#1285
1!
1(
b10011000 2
1)
0/
0.
0-
0*
#1290
0!
0(
#1295
1!
1(
b0 4
b1100 2
b0 5
0)
11
1-
#1300
0!
0(
#1305
1!
1(
03
b0 2
b0 6
#1310
0!
0(
#1315
1!
1(
01
10
1.
1,
b11 5
#1320
0!
0(
#1325
1!
1(
b11 4
b101 5
11
00
1/
0.
0-
0,
1+
#1330
0!
0(
#1335
1!
1(
b101 4
b0 5
01
10
1,
0+
1*
b101 5
#1340
0!
0(
#1345
1!
1(
b10 6
13
b10101010 2
11
#1350
0!
0(
#1355
1!
1(
b10100101 2
00
0/
1.
0,
#1360
0!
0(
#1365
1!
1(
b10000110 2
1/
1+
#1370
0!
0(
#1375
1!
1(
b11000111 2
1)
01
0/
0.
0+
0*
#1380
0!
0(
#1385
1!
1(
b0 4
b1001 2
b0 5
0)
11
1-
#1390
0!
0(
#1395
1!
1(
03
b0 2
b0 6
10
1.
0-
#1400
0!
0(
#1405
1!
1(
01
00
1/
0.
1,
1*
b10 5
#1410
0!
0(
#1415
1!
1(
b10 4
b100 5
10
0/
1-
0,
1+
0*
#1420
0!
0(
#1425
1!
1(
b100 4
b0 5
0-
1,
#1430
0!
0(
#1435
1!
1(
b0 4
1/
0,
0+
1*
#1440
0!
0(
#1445
1!
1(
11
00
0/
1,
1+
0*
#1450
0!
0(
#1455
1!
1(
10
1/
1.
0+
1*
b10 5
#1460
0!
0(
